[
    {
        "stop_id": 27415,
        "stop_code": 24833,
        "stop_name": "TAYLORS MILL RD & COUNTRY LA#",
        "stop_desc": "",
        "stop_lat": 40.30148,
        "stop_lon": -74.308223,
        "zone_id": 8192
    },
    {
        "stop_id": 27416,
        "stop_code": 24832,
        "stop_name": "TAYLORS MILLS RD AT TENNENT RD#",
        "stop_desc": "",
        "stop_lat": 40.299499,
        "stop_lon": -74.317212,
        "zone_id": 0
    },
    {
        "stop_id": 27417,
        "stop_code": 24831,
        "stop_name": "PEASE RD AT THOMPSON LANE#",
        "stop_desc": "",
        "stop_lat": 40.302779,
        "stop_lon": -74.319501,
        "zone_id": 0
    },
    {
        "stop_id": 27418,
        "stop_code": 24830,
        "stop_name": "PEASE RD AT MANOR CT#",
        "stop_desc": "",
        "stop_lat": 40.3055,
        "stop_lon": -74.320103,
        "zone_id": 0
    },
    {
        "stop_id": 41313,
        "stop_code": 24829,
        "stop_name": "PEASE RD AT GORDEN'S CORNER RD#",
        "stop_desc": "",
        "stop_lat": 40.309007,
        "stop_lon": -74.323073,
        "zone_id": 0
    },
    {
        "stop_id": 27420,
        "stop_code": 24828,
        "stop_name": "PEASE RD AT OLD QUEENS BLVD#",
        "stop_desc": "",
        "stop_lat": 40.313838,
        "stop_lon": -74.32494,
        "zone_id": 0
    },
    {
        "stop_id": 27421,
        "stop_code": 24826,
        "stop_name": "PEASE RD AT PINEBROOK RD#",
        "stop_desc": "",
        "stop_lat": 40.320519,
        "stop_lon": -74.327083,
        "zone_id": 0
    },
    {
        "stop_id": 27422,
        "stop_code": 24824,
        "stop_name": "UNION HILL RD AT PEASE RD#",
        "stop_desc": "",
        "stop_lat": 40.327858,
        "stop_lon": -74.331223,
        "zone_id": 0
    },
    {
        "stop_id": 27423,
        "stop_code": 24825,
        "stop_name": "UNION HILL RD AT BLENHEIM RD#",
        "stop_desc": "",
        "stop_lat": 40.332217,
        "stop_lon": -74.325632,
        "zone_id": 0
    },
    {
        "stop_id": 41314,
        "stop_code": 24797,
        "stop_name": "WILD TURKEY WAY AT PINECLUSTER CIRCLE",
        "stop_desc": "",
        "stop_lat": 40.333859,
        "stop_lon": -74.317361,
        "zone_id": 0
    },
    {
        "stop_id": 41315,
        "stop_code": 24798,
        "stop_name": "WILD TURKEY WAY AT BUILDING #13 DR",
        "stop_desc": "",
        "stop_lat": 40.333089,
        "stop_lon": -74.317051,
        "zone_id": 0
    },
    {
        "stop_id": 41316,
        "stop_code": 24799,
        "stop_name": "AMBERLY DR. WEST AT BUILDING #53 DR",
        "stop_desc": "",
        "stop_lat": 40.331779,
        "stop_lon": -74.317382,
        "zone_id": 0
    },
    {
        "stop_id": 41317,
        "stop_code": 24800,
        "stop_name": "AMBERLY DR. WEST AT BUILDING #81-85 DR",
        "stop_desc": "",
        "stop_lat": 40.328458,
        "stop_lon": -74.318953,
        "zone_id": 0
    },
    {
        "stop_id": 41318,
        "stop_code": 24801,
        "stop_name": "AMBERLY DR. WEST AT BUILDING #119-127 DR",
        "stop_desc": "",
        "stop_lat": 40.327148,
        "stop_lon": -74.316473,
        "zone_id": 0
    },
    {
        "stop_id": 27425,
        "stop_code": 24802,
        "stop_name": "COVERED BRIDGE",
        "stop_desc": "",
        "stop_lat": 40.327019,
        "stop_lon": -74.310691,
        "zone_id": 8195
    },
    {
        "stop_id": 41319,
        "stop_code": 24803,
        "stop_name": "AMBERLY DR. EAST AT BUILDING #147-152 DR",
        "stop_desc": "",
        "stop_lat": 40.32965,
        "stop_lon": -74.310851,
        "zone_id": 0
    },
    {
        "stop_id": 41320,
        "stop_code": 24804,
        "stop_name": "AMBERLY DR. EAST AT BUILDING #167-177 DR",
        "stop_desc": "",
        "stop_lat": 40.330858,
        "stop_lon": -74.313501,
        "zone_id": 0
    },
    {
        "stop_id": 27427,
        "stop_code": 24867,
        "stop_name": "UNION HILL RD PARK & RIDE",
        "stop_desc": "",
        "stop_lat": 40.339169,
        "stop_lon": -74.304502,
        "zone_id": 0
    },
    {
        "stop_id": 27367,
        "stop_code": 23563,
        "stop_name": "OLD BRIDGE PARK & RIDE (NORTHBOUND)",
        "stop_desc": "",
        "stop_lat": 40.446218,
        "stop_lon": -74.299461,
        "zone_id": 8192
    },
    {
        "stop_id": 43310,
        "stop_code": 31899,
        "stop_name": "PORT AUTHORITY DROP OFF",
        "stop_desc": "",
        "stop_lat": 40.756707,
        "stop_lon": -73.992134,
        "zone_id": 0
    },
    {
        "stop_id": 43274,
        "stop_code": 31858,
        "stop_name": "PORT AUTHORITY BUS TERMINAL",
        "stop_desc": "",
        "stop_lat": 40.756209,
        "stop_lon": -73.991001,
        "zone_id": 0
    },
    {
        "stop_id": 3511,
        "stop_code": 26229,
        "stop_name": "PORT AUTHORITY BUS TERMINAL",
        "stop_desc": "",
        "stop_lat": 40.756367,
        "stop_lon": -73.990753,
        "zone_id": 12336
    },
    {
        "stop_id": 27436,
        "stop_code": 24860,
        "stop_name": "RT-9 AT IVY HILL DR (MARLBORO GREENS)",
        "stop_desc": "",
        "stop_lat": 40.335388,
        "stop_lon": -74.307063,
        "zone_id": 0
    },
    {
        "stop_id": 41051,
        "stop_code": 24861,
        "stop_name": "US-9 AT JUG HANDLE @ BOUNDARY LINE",
        "stop_desc": "",
        "stop_lat": 40.329658,
        "stop_lon": -74.305841,
        "zone_id": 0
    },
    {
        "stop_id": 27437,
        "stop_code": 24805,
        "stop_name": "US-9 300'S OF COVERED BRIDGE BLVD",
        "stop_desc": "",
        "stop_lat": 40.32654,
        "stop_lon": -74.305631,
        "zone_id": 0
    },
    {
        "stop_id": 28765,
        "stop_code": 24806,
        "stop_name": "RT-9 AT GORDON'S CORNER",
        "stop_desc": "",
        "stop_lat": 40.312778,
        "stop_lon": -74.304383,
        "zone_id": 8192
    },
    {
        "stop_id": 28766,
        "stop_code": 24807,
        "stop_name": "US-9 AT TAYLORS MILL RD",
        "stop_desc": "",
        "stop_lat": 40.302598,
        "stop_lon": -74.303901,
        "zone_id": 0
    },
    {
        "stop_id": 27438,
        "stop_code": 24808,
        "stop_name": "US-9 AT PLAZA 9",
        "stop_desc": "",
        "stop_lat": 40.299098,
        "stop_lon": -74.302761,
        "zone_id": 0
    },
    {
        "stop_id": 27439,
        "stop_code": 24809,
        "stop_name": "US-9 AT SYMMES DR",
        "stop_desc": "",
        "stop_lat": 40.293338,
        "stop_lon": -74.29882,
        "zone_id": 0
    },
    {
        "stop_id": 27440,
        "stop_code": 24810,
        "stop_name": "US-9 AT CRAIG RD",
        "stop_desc": "",
        "stop_lat": 40.287189,
        "stop_lon": -74.295204,
        "zone_id": 0
    },
    {
        "stop_id": 28767,
        "stop_code": 24528,
        "stop_name": "RT-9 AT SCHIBANOFF RD",
        "stop_desc": "",
        "stop_lat": 40.27425,
        "stop_lon": -74.294281,
        "zone_id": 0
    },
    {
        "stop_id": 40378,
        "stop_code": 24529,
        "stop_name": "US-9 AT FREEHOLD RACEWAY MALL DR",
        "stop_desc": "",
        "stop_lat": 40.256147,
        "stop_lon": -74.290831,
        "zone_id": 0
    },
    {
        "stop_id": 27463,
        "stop_code": 24530,
        "stop_name": "FREEHOLD MALL",
        "stop_desc": "",
        "stop_lat": 40.245058,
        "stop_lon": -74.282103,
        "zone_id": 0
    },
    {
        "stop_id": 27444,
        "stop_code": 24532,
        "stop_name": "US-9 200'S OF SCHANCK RD",
        "stop_desc": "",
        "stop_lat": 40.239308,
        "stop_lon": -74.275622,
        "zone_id": 0
    },
    {
        "stop_id": 28772,
        "stop_code": 24533,
        "stop_name": "US-9 AT THREE BROOKS RD",
        "stop_desc": "",
        "stop_lat": 40.232367,
        "stop_lon": -74.27313,
        "zone_id": 0
    },
    {
        "stop_id": 28487,
        "stop_code": 24534,
        "stop_name": "US-9 AT CAMPBELL CT",
        "stop_desc": "",
        "stop_lat": 40.229559,
        "stop_lon": -74.272553,
        "zone_id": 0
    },
    {
        "stop_id": 28488,
        "stop_code": 24535,
        "stop_name": "RT-9 AT ADELPHIA RD",
        "stop_desc": "",
        "stop_lat": 40.22153,
        "stop_lon": -74.267593,
        "zone_id": 8192
    },
    {
        "stop_id": 28489,
        "stop_code": 24536,
        "stop_name": "US-9 AT SCENIC DR",
        "stop_desc": "",
        "stop_lat": 40.215268,
        "stop_lon": -74.261802,
        "zone_id": 0
    },
    {
        "stop_id": 28490,
        "stop_code": 24668,
        "stop_name": "RT-9 AT STRICKLAND RD PARK & RIDE",
        "stop_desc": "",
        "stop_lat": 40.209387,
        "stop_lon": -74.258262,
        "zone_id": 0
    },
    {
        "stop_id": 27332,
        "stop_code": 24692,
        "stop_name": "RT-9 AT STRICKLAND RD PARK & RIDE",
        "stop_desc": "",
        "stop_lat": 40.211169,
        "stop_lon": -74.258672,
        "zone_id": 8192
    },
    {
        "stop_id": 28491,
        "stop_code": 24669,
        "stop_name": "US-9 AT CASINO DR (HOWELL LANES)",
        "stop_desc": "",
        "stop_lat": 40.202049,
        "stop_lon": -74.255543,
        "zone_id": 0
    },
    {
        "stop_id": 41031,
        "stop_code": 24670,
        "stop_name": "US-9 165'S OF JUG HANDLE @ HOWELL GARAGE",
        "stop_desc": "",
        "stop_lat": 40.193299,
        "stop_lon": -74.252481,
        "zone_id": 0
    },
    {
        "stop_id": 28773,
        "stop_code": 24671,
        "stop_name": "U S RT 9 & WEST FARMS RD",
        "stop_desc": "",
        "stop_lat": 40.185405,
        "stop_lon": -74.24941,
        "zone_id": 336
    },
    {
        "stop_id": 28774,
        "stop_code": 24672,
        "stop_name": "US-9 AT SUNNYSIDE RD",
        "stop_desc": "",
        "stop_lat": 40.175619,
        "stop_lon": -74.242252,
        "zone_id": 0
    },
    {
        "stop_id": 27445,
        "stop_code": 24673,
        "stop_name": "US-9 AT W 5TH ST",
        "stop_desc": "",
        "stop_lat": 40.168878,
        "stop_lon": -74.238212,
        "zone_id": 0
    },
    {
        "stop_id": 27446,
        "stop_code": 24674,
        "stop_name": "US-9 AT STANLEY BLVD",
        "stop_desc": "",
        "stop_lat": 40.1604,
        "stop_lon": -74.233013,
        "zone_id": 0
    },
    {
        "stop_id": 28775,
        "stop_code": 24675,
        "stop_name": "RT-9 AT ALDRICH RD",
        "stop_desc": "",
        "stop_lat": 40.155248,
        "stop_lon": -74.22989,
        "zone_id": 0
    },
    {
        "stop_id": 27447,
        "stop_code": 24676,
        "stop_name": "US-9 AT FRIENDSHIP RD",
        "stop_desc": "",
        "stop_lat": 40.147909,
        "stop_lon": -74.226302,
        "zone_id": 0
    },
    {
        "stop_id": 28776,
        "stop_code": 24677,
        "stop_name": "US-9 AT NEW FRIENDSHIP RD",
        "stop_desc": "",
        "stop_lat": 40.140149,
        "stop_lon": -74.225261,
        "zone_id": 0
    },
    {
        "stop_id": 28777,
        "stop_code": 24678,
        "stop_name": "US-9 AT LANES MILL RD",
        "stop_desc": "",
        "stop_lat": 40.129728,
        "stop_lon": -74.223451,
        "zone_id": 0
    },
    {
        "stop_id": 40743,
        "stop_code": 24679,
        "stop_name": "US-9 AT ALEXANDER AVE",
        "stop_desc": "",
        "stop_lat": 40.11535,
        "stop_lon": -74.218961,
        "zone_id": 0
    },
    {
        "stop_id": 28778,
        "stop_code": 26383,
        "stop_name": "US-9 AT W COUNTY LINE RD",
        "stop_desc": "",
        "stop_lat": 40.1064,
        "stop_lon": -74.219541,
        "zone_id": 0
    },
    {
        "stop_id": 3526,
        "stop_code": 26384,
        "stop_name": "US-9 AT 10TH ST",
        "stop_desc": "",
        "stop_lat": 40.099398,
        "stop_lon": -74.218182,
        "zone_id": 0
    },
    {
        "stop_id": 3537,
        "stop_code": 26385,
        "stop_name": "US-9 AT 9TH ST",
        "stop_desc": "",
        "stop_lat": 40.098409,
        "stop_lon": -74.21803,
        "zone_id": 8195
    },
    {
        "stop_id": 3513,
        "stop_code": 26382,
        "stop_name": "CLIFTON AVE 90' S OF 6TH ST.",
        "stop_desc": "",
        "stop_lat": 40.095737,
        "stop_lon": -74.215403,
        "zone_id": 0
    },
    {
        "stop_id": 3539,
        "stop_code": 26412,
        "stop_name": "LAKEWOOD BUS TERMINAL",
        "stop_desc": "",
        "stop_lat": 40.091008,
        "stop_lon": -74.21257,
        "zone_id": 0
    },
    {
        "stop_id": 38104,
        "stop_code": 24693,
        "stop_name": "ALDRICH RD PARK & RIDE",
        "stop_desc": "",
        "stop_lat": 40.156169,
        "stop_lon": -74.227181,
        "zone_id": 8195
    },
    {
        "stop_id": 28768,
        "stop_code": 24494,
        "stop_name": "THROCKMORTON ST 2500' E of RT-9",
        "stop_desc": "",
        "stop_lat": 40.265218,
        "stop_lon": -74.287352,
        "zone_id": 8192
    },
    {
        "stop_id": 42349,
        "stop_code": 24495,
        "stop_name": "THROCKMORTON ST AT RHEA ST",
        "stop_desc": "",
        "stop_lat": 40.264379,
        "stop_lon": -74.284322,
        "zone_id": 0
    },
    {
        "stop_id": 28769,
        "stop_code": 24496,
        "stop_name": "THROCKMORTON ST AT MONMOUTH AVE",
        "stop_desc": "",
        "stop_lat": 40.26202,
        "stop_lon": -74.280131,
        "zone_id": 0
    },
    {
        "stop_id": 43091,
        "stop_code": 31548,
        "stop_name": "FREEHOLD CENTER",
        "stop_desc": "",
        "stop_lat": 40.259178,
        "stop_lon": -74.276451,
        "zone_id": 0
    },
    {
        "stop_id": 27442,
        "stop_code": 24508,
        "stop_name": "PARK AVE AT MAIN ST",
        "stop_desc": "",
        "stop_lat": 40.253528,
        "stop_lon": -74.283053,
        "zone_id": 0
    },
    {
        "stop_id": 27443,
        "stop_code": 24509,
        "stop_name": "PARK AVE AT BRENTWOOD AVE",
        "stop_desc": "",
        "stop_lat": 40.250889,
        "stop_lon": -74.276661,
        "zone_id": 0
    },
    {
        "stop_id": 28770,
        "stop_code": 24527,
        "stop_name": "RT-79 AT HELEN AVE",
        "stop_desc": "",
        "stop_lat": 40.247439,
        "stop_lon": -74.274743,
        "zone_id": 0
    },
    {
        "stop_id": 28771,
        "stop_code": 24526,
        "stop_name": "RT-79 AT SHOP RITE DR",
        "stop_desc": "",
        "stop_lat": 40.242939,
        "stop_lon": -74.275161,
        "zone_id": 0
    },
    {
        "stop_id": 27479,
        "stop_code": 24836,
        "stop_name": "UNION HILL RD AT IVANHOE DR#",
        "stop_desc": "",
        "stop_lat": 40.333927,
        "stop_lon": -74.323353,
        "zone_id": 0
    },
    {
        "stop_id": 27480,
        "stop_code": 24837,
        "stop_name": "UNION HILL RD AT CASTLE CT#",
        "stop_desc": "",
        "stop_lat": 40.331349,
        "stop_lon": -74.327131,
        "zone_id": 0
    },
    {
        "stop_id": 27481,
        "stop_code": 24838,
        "stop_name": "PEASE RD AT MADIGAN LANE#",
        "stop_desc": "",
        "stop_lat": 40.325139,
        "stop_lon": -74.329014,
        "zone_id": 0
    },
    {
        "stop_id": 30802,
        "stop_code": 24839,
        "stop_name": "PEASE RD AT PINEBROOK RD#",
        "stop_desc": "",
        "stop_lat": 40.32098,
        "stop_lon": -74.327392,
        "zone_id": 0
    },
    {
        "stop_id": 27482,
        "stop_code": 24840,
        "stop_name": "PEASE RD AT HAWTHORNE AVE#",
        "stop_desc": "",
        "stop_lat": 40.312698,
        "stop_lon": -74.324921,
        "zone_id": 0
    },
    {
        "stop_id": 27483,
        "stop_code": 24841,
        "stop_name": "PEASE RD AT TIMBER LANE#",
        "stop_desc": "",
        "stop_lat": 40.307919,
        "stop_lon": -74.32236,
        "zone_id": 0
    },
    {
        "stop_id": 27484,
        "stop_code": 24842,
        "stop_name": "PEASE RD AT INDEPENDENCE BLVD#",
        "stop_desc": "",
        "stop_lat": 40.303458,
        "stop_lon": -74.319653,
        "zone_id": 0
    },
    {
        "stop_id": 30803,
        "stop_code": 24843,
        "stop_name": "TAYLORS MILLS RD AT TENNENT RD#",
        "stop_desc": "",
        "stop_lat": 40.299329,
        "stop_lon": -74.31823,
        "zone_id": 0
    },
    {
        "stop_id": 30804,
        "stop_code": 24834,
        "stop_name": "TAYLORS MILL RD & COUNTRY LA#",
        "stop_desc": "",
        "stop_lat": 40.30131,
        "stop_lon": -74.308213,
        "zone_id": 8195
    },
    {
        "stop_id": 27398,
        "stop_code": 26341,
        "stop_name": "COOKS BRIDGE RD & MANHATTAN ST#",
        "stop_desc": "",
        "stop_lat": 40.113179,
        "stop_lon": -74.288631,
        "zone_id": 8192
    },
    {
        "stop_id": 27399,
        "stop_code": 26340,
        "stop_name": "NEW PROSPECT RD AT WEST COUNTY LINE RD#",
        "stop_desc": "",
        "stop_lat": 40.117528,
        "stop_lon": -74.253181,
        "zone_id": 0
    },
    {
        "stop_id": 31638,
        "stop_code": 24702,
        "stop_name": "US-9 AT NORTHWOODS PL",
        "stop_desc": "",
        "stop_lat": 40.160178,
        "stop_lon": -74.232552,
        "zone_id": 0
    },
    {
        "stop_id": 27325,
        "stop_code": 24685,
        "stop_name": "US-9 AT GEORGIA TAVERN RD",
        "stop_desc": "",
        "stop_lat": 40.16747,
        "stop_lon": -74.237002,
        "zone_id": 0
    },
    {
        "stop_id": 27326,
        "stop_code": 24686,
        "stop_name": "US-9 AT E 5TH ST",
        "stop_desc": "",
        "stop_lat": 40.16961,
        "stop_lon": -74.238334,
        "zone_id": 0
    },
    {
        "stop_id": 27327,
        "stop_code": 24687,
        "stop_name": "US-9 AT SUNNYSIDE RD",
        "stop_desc": "",
        "stop_lat": 40.176397,
        "stop_lon": -74.24232,
        "zone_id": 0
    },
    {
        "stop_id": 27328,
        "stop_code": 24688,
        "stop_name": "U S RT 9 & WEST FARMS RD",
        "stop_desc": "",
        "stop_lat": 40.185405,
        "stop_lon": -74.249407,
        "zone_id": 336
    },
    {
        "stop_id": 27329,
        "stop_code": 24689,
        "stop_name": "US-9 AT JUG HANDLE @ HOWELL GARAGE",
        "stop_desc": "",
        "stop_lat": 40.194078,
        "stop_lon": -74.252441,
        "zone_id": 0
    },
    {
        "stop_id": 27330,
        "stop_code": 24690,
        "stop_name": "RT-9 AT HOWELL GARAGE ENTRANCE",
        "stop_desc": "",
        "stop_lat": 40.196538,
        "stop_lon": -74.253311,
        "zone_id": 0
    },
    {
        "stop_id": 27331,
        "stop_code": 24691,
        "stop_name": "US-9 AT CASINO DR",
        "stop_desc": "",
        "stop_lat": 40.203178,
        "stop_lon": -74.255622,
        "zone_id": 8192
    },
    {
        "stop_id": 27333,
        "stop_code": 24537,
        "stop_name": "US-9 AT EDINBURGH DR",
        "stop_desc": "",
        "stop_lat": 40.21586,
        "stop_lon": -74.261832,
        "zone_id": 0
    },
    {
        "stop_id": 27334,
        "stop_code": 24538,
        "stop_name": "RT-9 AT ADELPHIA RD",
        "stop_desc": "",
        "stop_lat": 40.221258,
        "stop_lon": -74.266723,
        "zone_id": 0
    },
    {
        "stop_id": 27335,
        "stop_code": 24539,
        "stop_name": "US-9 225'S OF CAMPBELL CT",
        "stop_desc": "",
        "stop_lat": 40.228347,
        "stop_lon": -74.271951,
        "zone_id": 0
    },
    {
        "stop_id": 27336,
        "stop_code": 24540,
        "stop_name": "US-9 AT THREE BROOKS RD",
        "stop_desc": "",
        "stop_lat": 40.232948,
        "stop_lon": -74.272863,
        "zone_id": 0
    },
    {
        "stop_id": 27337,
        "stop_code": 24541,
        "stop_name": "US-9 AT SCHANCK RD",
        "stop_desc": "",
        "stop_lat": 40.240448,
        "stop_lon": -74.276301,
        "zone_id": 0
    },
    {
        "stop_id": 27394,
        "stop_code": 24545,
        "stop_name": "FREEHOLD MALL",
        "stop_desc": "",
        "stop_lat": 40.24591,
        "stop_lon": -74.282461,
        "zone_id": 8192
    },
    {
        "stop_id": 27344,
        "stop_code": 24543,
        "stop_name": "RT-9 AT SCHIBANOFF RD",
        "stop_desc": "",
        "stop_lat": 40.274779,
        "stop_lon": -74.294004,
        "zone_id": 0
    },
    {
        "stop_id": 27345,
        "stop_code": 24544,
        "stop_name": "US-9 AT E FREEHOLD RD",
        "stop_desc": "",
        "stop_lat": 40.28748,
        "stop_lon": -74.294921,
        "zone_id": 0
    },
    {
        "stop_id": 27346,
        "stop_code": 24811,
        "stop_name": "US-9 AT RYAN RD",
        "stop_desc": "",
        "stop_lat": 40.293169,
        "stop_lon": -74.298283,
        "zone_id": 0
    },
    {
        "stop_id": 27347,
        "stop_code": 24812,
        "stop_name": "US-9 AT SMALLWOOD LN",
        "stop_desc": "",
        "stop_lat": 40.299849,
        "stop_lon": -74.302833,
        "zone_id": 0
    },
    {
        "stop_id": 27348,
        "stop_code": 24813,
        "stop_name": "US-9 AT TAYLORS MILL RD",
        "stop_desc": "",
        "stop_lat": 40.302428,
        "stop_lon": -74.303551,
        "zone_id": 0
    },
    {
        "stop_id": 27349,
        "stop_code": 24814,
        "stop_name": "RT-9 AT GORDON'S CORNER",
        "stop_desc": "",
        "stop_lat": 40.31337,
        "stop_lon": -74.304151,
        "zone_id": 8192
    },
    {
        "stop_id": 3535,
        "stop_code": 26396,
        "stop_name": "US-9 AT 5TH ST",
        "stop_desc": "",
        "stop_lat": 40.095159,
        "stop_lon": -74.217171,
        "zone_id": 0
    },
    {
        "stop_id": 28764,
        "stop_code": 26397,
        "stop_name": "US-9 AT 10TH ST",
        "stop_desc": "",
        "stop_lat": 40.099609,
        "stop_lon": -74.218022,
        "zone_id": 0
    },
    {
        "stop_id": 3527,
        "stop_code": 26398,
        "stop_name": "US-9 AT E COUNTY LINE RD",
        "stop_desc": "",
        "stop_lat": 40.1066,
        "stop_lon": -74.219281,
        "zone_id": 0
    },
    {
        "stop_id": 27319,
        "stop_code": 24680,
        "stop_name": "US-9 AT ALEXANDER AVE",
        "stop_desc": "",
        "stop_lat": 40.115169,
        "stop_lon": -74.218661,
        "zone_id": 0
    },
    {
        "stop_id": 27320,
        "stop_code": 24681,
        "stop_name": "US-9 AT LANES MILL RD",
        "stop_desc": "",
        "stop_lat": 40.129218,
        "stop_lon": -74.223033,
        "zone_id": 0
    },
    {
        "stop_id": 27321,
        "stop_code": 24682,
        "stop_name": "US-9 AT NEW FRIENDSHIP RD",
        "stop_desc": "",
        "stop_lat": 40.139779,
        "stop_lon": -74.224913,
        "zone_id": 0
    },
    {
        "stop_id": 27322,
        "stop_code": 24683,
        "stop_name": "US-9 175'S OF SALEM HILL RD",
        "stop_desc": "",
        "stop_lat": 40.147208,
        "stop_lon": -74.22585,
        "zone_id": 0
    },
    {
        "stop_id": 27323,
        "stop_code": 24684,
        "stop_name": "RT-9 AT ALDRICH RD",
        "stop_desc": "",
        "stop_lat": 40.15507,
        "stop_lon": -74.229433,
        "zone_id": 0
    },
    {
        "stop_id": 41327,
        "stop_code": 24566,
        "stop_name": "WEMROCK RD AT HUTCHINSON DR#",
        "stop_desc": "",
        "stop_lat": 40.244479,
        "stop_lon": -74.304643,
        "zone_id": 0
    },
    {
        "stop_id": 27476,
        "stop_code": 24557,
        "stop_name": "ADELPHIA RD AT GEORGIA RD#",
        "stop_desc": "",
        "stop_lat": 40.22079,
        "stop_lon": -74.291422,
        "zone_id": 8192
    },
    {
        "stop_id": 27403,
        "stop_code": 24558,
        "stop_name": "ADELPHIA RD AT OLD POST RD#",
        "stop_desc": "",
        "stop_lat": 40.221099,
        "stop_lon": -74.279002,
        "zone_id": 8192
    },
    {
        "stop_id": 30801,
        "stop_code": 24559,
        "stop_name": "ELTON-ADELPHIA & JACKSON MILLS RDS#",
        "stop_desc": "",
        "stop_lat": 40.221247,
        "stop_lon": -74.270502,
        "zone_id": 8192
    },
    {
        "stop_id": 27464,
        "stop_code": 26346,
        "stop_name": "WEST COUNTY LINE RD AT NEW PROSPECT RD#",
        "stop_desc": "",
        "stop_lat": 40.117649,
        "stop_lon": -74.25376,
        "zone_id": 0
    },
    {
        "stop_id": 27465,
        "stop_code": 26339,
        "stop_name": "COOKS BRIDGE RD & MANHATTAN ST#",
        "stop_desc": "",
        "stop_lat": 40.112979,
        "stop_lon": -74.288733,
        "zone_id": 0
    },
    {
        "stop_id": 31060,
        "stop_code": 24542,
        "stop_name": "US-9 AT FREEHOLD RACEWAY MALL DR",
        "stop_desc": "",
        "stop_lat": 40.256449,
        "stop_lon": -74.290581,
        "zone_id": 8195
    },
    {
        "stop_id": 27397,
        "stop_code": 24505,
        "stop_name": "MAIN ST AT PARK AVE",
        "stop_desc": "",
        "stop_lat": 40.254139,
        "stop_lon": -74.282832,
        "zone_id": 0
    },
    {
        "stop_id": 27341,
        "stop_code": 24502,
        "stop_name": "FREEHOLD CENTER",
        "stop_desc": "",
        "stop_lat": 40.259219,
        "stop_lon": -74.27644,
        "zone_id": 0
    },
    {
        "stop_id": 27342,
        "stop_code": 24497,
        "stop_name": "THROCKMORTON ST AT MONMOUTH AVE",
        "stop_desc": "",
        "stop_lat": 40.262077,
        "stop_lon": -74.280051,
        "zone_id": 0
    },
    {
        "stop_id": 42348,
        "stop_code": 24498,
        "stop_name": "THROCKMORTON ST AT RHEA ST",
        "stop_desc": "",
        "stop_lat": 40.2645,
        "stop_lon": -74.284454,
        "zone_id": 0
    },
    {
        "stop_id": 27343,
        "stop_code": 24499,
        "stop_name": "THROCKMORTON ST 2600' E of RT-9",
        "stop_desc": "",
        "stop_lat": 40.265248,
        "stop_lon": -74.28705,
        "zone_id": 8192
    },
    {
        "stop_id": 27350,
        "stop_code": 24815,
        "stop_name": "US-9 AT JUG HNDL @ COVERED BRIDGE",
        "stop_desc": "",
        "stop_lat": 40.329439,
        "stop_lon": -74.305451,
        "zone_id": 0
    },
    {
        "stop_id": 27351,
        "stop_code": 24862,
        "stop_name": "RT-9 AT UNION HILL RD",
        "stop_desc": "",
        "stop_lat": 40.338849,
        "stop_lon": -74.307032,
        "zone_id": 0
    },
    {
        "stop_id": 27352,
        "stop_code": 24863,
        "stop_name": "US-9 AT WILLOW LN",
        "stop_desc": "",
        "stop_lat": 40.346009,
        "stop_lon": -74.307771,
        "zone_id": 0
    },
    {
        "stop_id": 27353,
        "stop_code": 24864,
        "stop_name": "US-9 AT ROBERTSVILLE RD",
        "stop_desc": "",
        "stop_lat": 40.352898,
        "stop_lon": -74.306833,
        "zone_id": 0
    },
    {
        "stop_id": 27354,
        "stop_code": 24865,
        "stop_name": "US-9 870'S OF TEXAS RD",
        "stop_desc": "",
        "stop_lat": 40.361659,
        "stop_lon": -74.304821,
        "zone_id": 0
    },
    {
        "stop_id": 27355,
        "stop_code": 23551,
        "stop_name": "U S RT 9 & TEXAS RD",
        "stop_desc": "",
        "stop_lat": 40.36438,
        "stop_lon": -74.304902,
        "zone_id": 8192
    },
    {
        "stop_id": 27356,
        "stop_code": 23552,
        "stop_name": "US-9 AT SPRING VALLEY RD",
        "stop_desc": "",
        "stop_lat": 40.373908,
        "stop_lon": -74.306411,
        "zone_id": 0
    },
    {
        "stop_id": 27357,
        "stop_code": 23553,
        "stop_name": "US-9 AT FERRY RD",
        "stop_desc": "",
        "stop_lat": 40.383899,
        "stop_lon": -74.307981,
        "zone_id": 0
    },
    {
        "stop_id": 27358,
        "stop_code": 23554,
        "stop_name": "US-9 135'S OF INVERNESS DR",
        "stop_desc": "",
        "stop_lat": 40.386349,
        "stop_lon": -74.307931,
        "zone_id": 0
    },
    {
        "stop_id": 27359,
        "stop_code": 23555,
        "stop_name": "US-9 AT CINDY ST",
        "stop_desc": "",
        "stop_lat": 40.38984,
        "stop_lon": -74.30772,
        "zone_id": 0
    },
    {
        "stop_id": 27360,
        "stop_code": 23556,
        "stop_name": "RT-9 NORTHBOUND AT TICETOWN RD",
        "stop_desc": "",
        "stop_lat": 40.395468,
        "stop_lon": -74.307232,
        "zone_id": 2384
    },
    {
        "stop_id": 27361,
        "stop_code": 23557,
        "stop_name": "US-9 AT PHILLIPS DR",
        "stop_desc": "",
        "stop_lat": 40.406939,
        "stop_lon": -74.305432,
        "zone_id": 0
    },
    {
        "stop_id": 27362,
        "stop_code": 23558,
        "stop_name": "US-9 AT FAIRWAY LANE",
        "stop_desc": "",
        "stop_lat": 40.40917,
        "stop_lon": -74.30547,
        "zone_id": 0
    },
    {
        "stop_id": 27363,
        "stop_code": 23559,
        "stop_name": "RT-9 AT JAKE BROWN RD",
        "stop_desc": "",
        "stop_lat": 40.416078,
        "stop_lon": -74.304693,
        "zone_id": 0
    },
    {
        "stop_id": 27364,
        "stop_code": 23560,
        "stop_name": "US-9 AT SCHULMEISTER RD",
        "stop_desc": "",
        "stop_lat": 40.422287,
        "stop_lon": -74.303832,
        "zone_id": 0
    },
    {
        "stop_id": 27365,
        "stop_code": 23561,
        "stop_name": "US-9 AT OLD MILL RD",
        "stop_desc": "",
        "stop_lat": 40.430969,
        "stop_lon": -74.302614,
        "zone_id": 0
    },
    {
        "stop_id": 27366,
        "stop_code": 23562,
        "stop_name": "RT-9 AT PERRINE RD",
        "stop_desc": "",
        "stop_lat": 40.435139,
        "stop_lon": -74.301331,
        "zone_id": 8192
    },
    {
        "stop_id": 42497,
        "stop_code": 24525,
        "stop_name": "RT-79 250' N OF SHOP RITE DR.",
        "stop_desc": "",
        "stop_lat": 40.243287,
        "stop_lon": -74.274993,
        "zone_id": 0
    },
    {
        "stop_id": 27339,
        "stop_code": 24524,
        "stop_name": "RT-79 AT HELEN AVE",
        "stop_desc": "",
        "stop_lat": 40.247529,
        "stop_lon": -74.274602,
        "zone_id": 0
    },
    {
        "stop_id": 27340,
        "stop_code": 24512,
        "stop_name": "PARK AVE AT STILLWELL PL",
        "stop_desc": "",
        "stop_lat": 40.251188,
        "stop_lon": -74.277261,
        "zone_id": 0
    },
    {
        "stop_id": 27429,
        "stop_code": 23564,
        "stop_name": "OLD BRIDGE PARK & RIDE (SOUTHBOUND)",
        "stop_desc": "",
        "stop_lat": 40.44735,
        "stop_lon": -74.301312,
        "zone_id": 8192
    },
    {
        "stop_id": 28477,
        "stop_code": 23565,
        "stop_name": "RT-9 AT PERRINE RD",
        "stop_desc": "",
        "stop_lat": 40.43463,
        "stop_lon": -74.301973,
        "zone_id": 0
    },
    {
        "stop_id": 28478,
        "stop_code": 23566,
        "stop_name": "US-9 AT OLD MILL RD",
        "stop_desc": "",
        "stop_lat": 40.431678,
        "stop_lon": -74.302931,
        "zone_id": 0
    },
    {
        "stop_id": 28479,
        "stop_code": 23567,
        "stop_name": "US-9 AT SCHULMEISTER RD",
        "stop_desc": "",
        "stop_lat": 40.42263,
        "stop_lon": -74.3043,
        "zone_id": 0
    },
    {
        "stop_id": 28480,
        "stop_code": 23568,
        "stop_name": "RT-9 AT JAKE BROWN RD",
        "stop_desc": "",
        "stop_lat": 40.41624,
        "stop_lon": -74.305163,
        "zone_id": 0
    },
    {
        "stop_id": 28481,
        "stop_code": 23569,
        "stop_name": "US-9 AT FAIRWAY LN",
        "stop_desc": "",
        "stop_lat": 40.409578,
        "stop_lon": -74.305952,
        "zone_id": 0
    },
    {
        "stop_id": 27430,
        "stop_code": 23570,
        "stop_name": "US-9 AT EHLERS LN",
        "stop_desc": "",
        "stop_lat": 40.40629,
        "stop_lon": -74.305881,
        "zone_id": 0
    },
    {
        "stop_id": 27431,
        "stop_code": 23571,
        "stop_name": "RT-9 SERVICE RD AT THROCKMORTON LA",
        "stop_desc": "",
        "stop_lat": 40.396819,
        "stop_lon": -74.308033,
        "zone_id": 0
    },
    {
        "stop_id": 28482,
        "stop_code": 23572,
        "stop_name": "US-9 AT CINDY ST",
        "stop_desc": "",
        "stop_lat": 40.389327,
        "stop_lon": -74.308203,
        "zone_id": 0
    },
    {
        "stop_id": 28484,
        "stop_code": 23574,
        "stop_name": "US-9 AT FERRY RD",
        "stop_desc": "",
        "stop_lat": 40.383729,
        "stop_lon": -74.308472,
        "zone_id": 0
    },
    {
        "stop_id": 28485,
        "stop_code": 23575,
        "stop_name": "US-9 AT SPRING VALLEY RD",
        "stop_desc": "",
        "stop_lat": 40.373998,
        "stop_lon": -74.307022,
        "zone_id": 0
    },
    {
        "stop_id": 41030,
        "stop_code": 24855,
        "stop_name": "US-9 AT TEXAS RD",
        "stop_desc": "",
        "stop_lat": 40.363429,
        "stop_lon": -74.305313,
        "zone_id": 0
    },
    {
        "stop_id": 27432,
        "stop_code": 24856,
        "stop_name": "US-9 AT ROBERTSVILLE RD",
        "stop_desc": "",
        "stop_lat": 40.353309,
        "stop_lon": -74.307153,
        "zone_id": 0
    },
    {
        "stop_id": 27433,
        "stop_code": 24857,
        "stop_name": "US-9 AT SANDBURG DR",
        "stop_desc": "",
        "stop_lat": 40.34676,
        "stop_lon": -74.308041,
        "zone_id": 0
    },
    {
        "stop_id": 27434,
        "stop_code": 24858,
        "stop_name": "US-9 AT LONGFELLOW TER",
        "stop_desc": "",
        "stop_lat": 40.343779,
        "stop_lon": -74.308211,
        "zone_id": 0
    },
    {
        "stop_id": 27368,
        "stop_code": 24556,
        "stop_name": "CR-522 at WEMROCK RD #",
        "stop_desc": "",
        "stop_lat": 40.26989,
        "stop_lon": -74.304732,
        "zone_id": 0
    },
    {
        "stop_id": 27369,
        "stop_code": 24819,
        "stop_name": "RT-522 AT TENNENT RD#",
        "stop_desc": "",
        "stop_lat": 40.281448,
        "stop_lon": -74.33032,
        "zone_id": 8192
    },
    {
        "stop_id": 27370,
        "stop_code": 24818,
        "stop_name": "CR-522 at TAYLORS MILLS RD #",
        "stop_desc": "",
        "stop_lat": 40.290119,
        "stop_lon": -74.34323,
        "zone_id": 0
    },
    {
        "stop_id": 27371,
        "stop_code": 24817,
        "stop_name": "CR-522 at FARM TREE RD",
        "stop_desc": "",
        "stop_lat": 40.292379,
        "stop_lon": -74.349143,
        "zone_id": 0
    },
    {
        "stop_id": 27372,
        "stop_code": 24470,
        "stop_name": "TENNENT AVE AT HARRISON ST#",
        "stop_desc": "",
        "stop_lat": 40.295407,
        "stop_lon": -74.355722,
        "zone_id": 0
    },
    {
        "stop_id": 27373,
        "stop_code": 24475,
        "stop_name": "TENNENT AVE AT MAIN ST#",
        "stop_desc": "",
        "stop_lat": 40.295509,
        "stop_lon": -74.358193,
        "zone_id": 0
    },
    {
        "stop_id": 27374,
        "stop_code": 24469,
        "stop_name": "MAIN ST AT WATER ST",
        "stop_desc": "",
        "stop_lat": 40.296928,
        "stop_lon": -74.35835,
        "zone_id": 0
    },
    {
        "stop_id": 27375,
        "stop_code": 24476,
        "stop_name": "MAIN ST AT MATAWAN ST#",
        "stop_desc": "",
        "stop_lat": 40.302329,
        "stop_lon": -74.356773,
        "zone_id": 0
    },
    {
        "stop_id": 41321,
        "stop_code": 24816,
        "stop_name": "CR-527 (WILSON AVE) AT LONE STAR LN",
        "stop_desc": "",
        "stop_lat": 40.309728,
        "stop_lon": -74.359843,
        "zone_id": 0
    },
    {
        "stop_id": 27377,
        "stop_code": 24835,
        "stop_name": "CR-527 at SOBECKO RD #",
        "stop_desc": "",
        "stop_lat": 40.312679,
        "stop_lon": -74.361142,
        "zone_id": 0
    },
    {
        "stop_id": 41322,
        "stop_code": 23411,
        "stop_name": "CR-527 at UNION HILL RD #",
        "stop_desc": "",
        "stop_lat": 40.322969,
        "stop_lon": -74.361362,
        "zone_id": 0
    },
    {
        "stop_id": 41323,
        "stop_code": 23419,
        "stop_name": "CR-527 at MOUNTS MILLS RD #",
        "stop_desc": "",
        "stop_lat": 40.325608,
        "stop_lon": -74.360992,
        "zone_id": 0
    },
    {
        "stop_id": 43415,
        "stop_code": 32218,
        "stop_name": "CR-527 at COLORADO BLVD",
        "stop_desc": "",
        "stop_lat": 40.347725,
        "stop_lon": -74.35718,
        "zone_id": 336
    },
    {
        "stop_id": 41324,
        "stop_code": 23621,
        "stop_name": "CR-527 at MAPLETON RD",
        "stop_desc": "",
        "stop_lat": 40.35126,
        "stop_lon": -74.356221,
        "zone_id": 0
    },
    {
        "stop_id": 39454,
        "stop_code": 23613,
        "stop_name": "CR-527 at CANNON RD",
        "stop_desc": "",
        "stop_lat": 40.354449,
        "stop_lon": -74.355483,
        "zone_id": 0
    },
    {
        "stop_id": 27381,
        "stop_code": 23622,
        "stop_name": "CR-527 at TEXAS RD",
        "stop_desc": "",
        "stop_lat": 40.357148,
        "stop_lon": -74.354832,
        "zone_id": 0
    },
    {
        "stop_id": 27383,
        "stop_code": 23623,
        "stop_name": "CR-527 at PLEASANT VALLEY RD",
        "stop_desc": "",
        "stop_lat": 40.375768,
        "stop_lon": -74.356721,
        "zone_id": 0
    },
    {
        "stop_id": 27384,
        "stop_code": 23624,
        "stop_name": "CR-527 at TORTORICE RD",
        "stop_desc": "",
        "stop_lat": 40.387009,
        "stop_lon": -74.358382,
        "zone_id": 0
    },
    {
        "stop_id": 27385,
        "stop_code": 23625,
        "stop_name": "ENGLISHTOWN & COLLINS RDS",
        "stop_desc": "",
        "stop_lat": 40.390138,
        "stop_lon": -74.358832,
        "zone_id": 8192
    },
    {
        "stop_id": 27386,
        "stop_code": 23626,
        "stop_name": "CR-527 at MIMI RD",
        "stop_desc": "",
        "stop_lat": 40.391999,
        "stop_lon": -74.359112,
        "zone_id": 0
    },
    {
        "stop_id": 27387,
        "stop_code": 23627,
        "stop_name": "CR-527 at HILLARD RD",
        "stop_desc": "",
        "stop_lat": 40.394748,
        "stop_lon": -74.359532,
        "zone_id": 8192
    },
    {
        "stop_id": 27389,
        "stop_code": 23629,
        "stop_name": "CR-527 at BELMONT AVE",
        "stop_desc": "",
        "stop_lat": 40.401398,
        "stop_lon": -74.360641,
        "zone_id": 0
    },
    {
        "stop_id": 41326,
        "stop_code": 23630,
        "stop_name": "CR-527 at RANDOLPH AVE",
        "stop_desc": "",
        "stop_lat": 40.403478,
        "stop_lon": -74.360963,
        "zone_id": 0
    },
    {
        "stop_id": 27392,
        "stop_code": 23631,
        "stop_name": "CR-527 at JAMES AVE",
        "stop_desc": "",
        "stop_lat": 40.406629,
        "stop_lon": -74.361424,
        "zone_id": 0
    },
    {
        "stop_id": 41053,
        "stop_code": 23667,
        "stop_name": "CR-516 at OLD MATAWAN RD",
        "stop_desc": "",
        "stop_lat": 40.410088,
        "stop_lon": -74.3573,
        "zone_id": 0
    },
    {
        "stop_id": 3434,
        "stop_code": 23597,
        "stop_name": "CR-516 at RIDGE RD",
        "stop_desc": "",
        "stop_lat": 40.410238,
        "stop_lon": -74.355352,
        "zone_id": 0
    },
    {
        "stop_id": 3435,
        "stop_code": 23598,
        "stop_name": "CR-516 & OWENS RD",
        "stop_desc": "",
        "stop_lat": 40.406909,
        "stop_lon": -74.335752,
        "zone_id": 0
    },
    {
        "stop_id": 3436,
        "stop_code": 23599,
        "stop_name": "CR-516 at WORTH PL",
        "stop_desc": "",
        "stop_lat": 40.406018,
        "stop_lon": -74.33234,
        "zone_id": 0
    },
    {
        "stop_id": 3437,
        "stop_code": 23600,
        "stop_name": "RT-516 AT GAUB RD",
        "stop_desc": "",
        "stop_lat": 40.40458,
        "stop_lon": -74.326872,
        "zone_id": 0
    },
    {
        "stop_id": 27393,
        "stop_code": 23601,
        "stop_name": "RT-516 AT ANGELA DR",
        "stop_desc": "",
        "stop_lat": 40.403549,
        "stop_lon": -74.321461,
        "zone_id": 0
    },
    {
        "stop_id": 3438,
        "stop_code": 23602,
        "stop_name": "RT-516 AT BUSHNELL RD",
        "stop_desc": "",
        "stop_lat": 40.401859,
        "stop_lon": -74.312793,
        "zone_id": 0
    },
    {
        "stop_id": 27402,
        "stop_code": 24560,
        "stop_name": "ELTON-ADELPHIA & JACKSON MILLS RDS#",
        "stop_desc": "",
        "stop_lat": 40.221398,
        "stop_lon": -74.270512,
        "zone_id": 8192
    },
    {
        "stop_id": 41311,
        "stop_code": 24561,
        "stop_name": "ADELPHIA RD AT OLD POST RD#",
        "stop_desc": "",
        "stop_lat": 40.22122,
        "stop_lon": -74.27843,
        "zone_id": 0
    },
    {
        "stop_id": 27404,
        "stop_code": 24562,
        "stop_name": "ADELPHIA RD AT COVENTRY DR#",
        "stop_desc": "",
        "stop_lat": 40.22102,
        "stop_lon": -74.287092,
        "zone_id": 0
    },
    {
        "stop_id": 27405,
        "stop_code": 24563,
        "stop_name": "ADELPHIA RD AT STILLWELLS CORNER RD#",
        "stop_desc": "",
        "stop_lat": 40.220979,
        "stop_lon": -74.293491,
        "zone_id": 0
    },
    {
        "stop_id": 27428,
        "stop_code": 24565,
        "stop_name": "WEMROCK RD AT HUTCHINSON DR#",
        "stop_desc": "",
        "stop_lat": 40.246019,
        "stop_lon": -74.305721,
        "zone_id": 8192
    },
    {
        "stop_id": 27449,
        "stop_code": 23616,
        "stop_name": "RT-516 AT BUSHNELL RD",
        "stop_desc": "",
        "stop_lat": 40.40193,
        "stop_lon": -74.312353,
        "zone_id": 8192
    },
    {
        "stop_id": 3439,
        "stop_code": 23617,
        "stop_name": "RT-516 AT GAUB RD",
        "stop_desc": "",
        "stop_lat": 40.404139,
        "stop_lon": -74.323821,
        "zone_id": 0
    },
    {
        "stop_id": 3440,
        "stop_code": 23618,
        "stop_name": "CR-516 at PATIO GREENS DR",
        "stop_desc": "",
        "stop_lat": 40.404769,
        "stop_lon": -74.327122,
        "zone_id": 0
    },
    {
        "stop_id": 3441,
        "stop_code": 23619,
        "stop_name": "CR-516 & OWENS RD",
        "stop_desc": "",
        "stop_lat": 40.406218,
        "stop_lon": -74.332573,
        "zone_id": 0
    },
    {
        "stop_id": 41052,
        "stop_code": 30249,
        "stop_name": "CR-516 100' W of MANNINO PARK DRIVE",
        "stop_desc": "",
        "stop_lat": 40.407769,
        "stop_lon": -74.336961,
        "zone_id": 0
    },
    {
        "stop_id": 3442,
        "stop_code": 23620,
        "stop_name": "CR-516 at RIDGE RD",
        "stop_desc": "",
        "stop_lat": 40.41034,
        "stop_lon": -74.356021,
        "zone_id": 0
    },
    {
        "stop_id": 27451,
        "stop_code": 23633,
        "stop_name": "CR-527 at THIRD ST",
        "stop_desc": "",
        "stop_lat": 40.406509,
        "stop_lon": -74.361572,
        "zone_id": 0
    },
    {
        "stop_id": 27453,
        "stop_code": 23634,
        "stop_name": "CR-527 at FIFTH ST",
        "stop_desc": "",
        "stop_lat": 40.4033,
        "stop_lon": -74.361101,
        "zone_id": 0
    },
    {
        "stop_id": 41328,
        "stop_code": 23635,
        "stop_name": "CR-527 at SIXTH ST",
        "stop_desc": "",
        "stop_lat": 40.400809,
        "stop_lon": -74.3607,
        "zone_id": 0
    },
    {
        "stop_id": 30780,
        "stop_code": 23636,
        "stop_name": "CR-527 at HILLIARD RD",
        "stop_desc": "",
        "stop_lat": 40.394068,
        "stop_lon": -74.359592,
        "zone_id": 0
    },
    {
        "stop_id": 27455,
        "stop_code": 23637,
        "stop_name": "CR-527 at BROOKSIDE AVE",
        "stop_desc": "",
        "stop_lat": 40.392838,
        "stop_lon": -74.359411,
        "zone_id": 0
    },
    {
        "stop_id": 27457,
        "stop_code": 23638,
        "stop_name": "ENGLISHTOWN & COLLINS RDS",
        "stop_desc": "",
        "stop_lat": 40.390289,
        "stop_lon": -74.359032,
        "zone_id": 8192
    },
    {
        "stop_id": 30781,
        "stop_code": 23639,
        "stop_name": "CR-527 at TORTORICE RD",
        "stop_desc": "",
        "stop_lat": 40.386598,
        "stop_lon": -74.358472,
        "zone_id": 0
    },
    {
        "stop_id": 30782,
        "stop_code": 23640,
        "stop_name": "CR-527 at PLEASANT VALLEY RD",
        "stop_desc": "",
        "stop_lat": 40.375089,
        "stop_lon": -74.35678,
        "zone_id": 0
    },
    {
        "stop_id": 30783,
        "stop_code": 23641,
        "stop_name": "CR-527 200' N of TEXAS RD.",
        "stop_desc": "",
        "stop_lat": 40.357368,
        "stop_lon": -74.35488,
        "zone_id": 0
    },
    {
        "stop_id": 39453,
        "stop_code": 23642,
        "stop_name": "CR-527 at CANNON RD",
        "stop_desc": "",
        "stop_lat": 40.353879,
        "stop_lon": -74.355721,
        "zone_id": 0
    },
    {
        "stop_id": 40777,
        "stop_code": 23632,
        "stop_name": "CR-527 at MAPLETON RD",
        "stop_desc": "",
        "stop_lat": 40.351418,
        "stop_lon": -74.356342,
        "zone_id": 0
    },
    {
        "stop_id": 43416,
        "stop_code": 32219,
        "stop_name": "CR-527 at COLORADO BLVD",
        "stop_desc": "",
        "stop_lat": 40.347725,
        "stop_lon": -74.35718,
        "zone_id": 336
    },
    {
        "stop_id": 30788,
        "stop_code": 23413,
        "stop_name": "CR-527 at MOUNTS MILLS RD #",
        "stop_desc": "",
        "stop_lat": 40.325528,
        "stop_lon": -74.361093,
        "zone_id": 0
    },
    {
        "stop_id": 27378,
        "stop_code": 23412,
        "stop_name": "CR-527 at UNION HILL RD #",
        "stop_desc": "",
        "stop_lat": 40.323007,
        "stop_lon": -74.36148,
        "zone_id": 8192
    },
    {
        "stop_id": 30785,
        "stop_code": 24827,
        "stop_name": "CR-527 at SOBECKO RD #",
        "stop_desc": "",
        "stop_lat": 40.312857,
        "stop_lon": -74.36132,
        "zone_id": 0
    },
    {
        "stop_id": 30786,
        "stop_code": 24823,
        "stop_name": "CR-527 at HERBERT DR #",
        "stop_desc": "",
        "stop_lat": 40.309479,
        "stop_lon": -74.359932,
        "zone_id": 0
    },
    {
        "stop_id": 30787,
        "stop_code": 24474,
        "stop_name": "MAIN ST AT MATAWAN ST#",
        "stop_desc": "",
        "stop_lat": 40.302239,
        "stop_lon": -74.356842,
        "zone_id": 0
    },
    {
        "stop_id": 28779,
        "stop_code": 24468,
        "stop_name": "MAIN ST AT WATER ST",
        "stop_desc": "",
        "stop_lat": 40.296747,
        "stop_lon": -74.35847,
        "zone_id": 8195
    },
    {
        "stop_id": 27460,
        "stop_code": 24473,
        "stop_name": "TENNENT ST AT MAIN ST#",
        "stop_desc": "",
        "stop_lat": 40.295399,
        "stop_lon": -74.357982,
        "zone_id": 0
    },
    {
        "stop_id": 27461,
        "stop_code": 24472,
        "stop_name": "TENNENT ST AT VICTORY DR#",
        "stop_desc": "",
        "stop_lat": 40.295328,
        "stop_lon": -74.356542,
        "zone_id": 0
    },
    {
        "stop_id": 27462,
        "stop_code": 24471,
        "stop_name": "TENNENT ST AT IRVING PL#",
        "stop_desc": "",
        "stop_lat": 40.29512,
        "stop_lon": -74.354413,
        "zone_id": 0
    },
    {
        "stop_id": 30794,
        "stop_code": 24822,
        "stop_name": "CR-522 at FARM TREE RD #",
        "stop_desc": "",
        "stop_lat": 40.292289,
        "stop_lon": -74.349241,
        "zone_id": 0
    },
    {
        "stop_id": 30795,
        "stop_code": 24821,
        "stop_name": "CR-522 at TAYLORS MILLS RD #",
        "stop_desc": "",
        "stop_lat": 40.290088,
        "stop_lon": -74.343712,
        "zone_id": 0
    },
    {
        "stop_id": 30796,
        "stop_code": 24820,
        "stop_name": "RT-522 AT TENNENT RD#",
        "stop_desc": "",
        "stop_lat": 40.281399,
        "stop_lon": -74.330493,
        "zone_id": 0
    },
    {
        "stop_id": 30797,
        "stop_code": 24555,
        "stop_name": "CR-522 at WEMROCK RD #",
        "stop_desc": "",
        "stop_lat": 40.269868,
        "stop_lon": -74.305152,
        "zone_id": 0
    }
]